{
	"info": {
		"_postman_id": "77056642-8619-42eb-8ebc-2a6b26ca8475",
		"name": "TP_1_P2_DAI_Bebczuk_Susel",
		"schema": "https://schema.getpostman.com/json/collection/v2.1.0/collection.json"
	},
	"item": [
		{
			"name": "Parte_2_Punto_1",
			"request": {
				"method": "GET",
				"header": [],
				"url": {
					"raw": "https://pokeapi.co/api/v2/pokemon/pikachu",
					"protocol": "https",
					"host": [
						"pokeapi",
						"co"
					],
					"path": [
						"api",
						"v2",
						"pokemon",
						"pikachu"
					]
				}
			},
			"response": []
		},
		{
			"name": "Parte_2_Punto_2",
			"request": {
				"method": "GET",
				"header": [],
				"url": {
					"raw": "https://pokeapi.co/api/v2/type",
					"protocol": "https",
					"host": [
						"pokeapi",
						"co"
					],
					"path": [
						"api",
						"v2",
						"type"
					]
				}
			},
			"response": []
		},
		{
			"name": "Parte_2_Punto_3",
			"request": {
				"method": "GET",
				"header": [],
				"url": {
					"raw": "https://pokeapi.co/api/v2/pokemon/150",
					"protocol": "https",
					"host": [
						"pokeapi",
						"co"
					],
					"path": [
						"api",
						"v2",
						"pokemon",
						"150"
					]
				}
			},
			"response": []
		},
		{
			"name": "Parte_2_Punto_4",
			"request": {
				"method": "GET",
				"header": [],
				"url": {
					"raw": "https://pokeapi.co/api/v2/ability?pokemon=charizard",
					"protocol": "https",
					"host": [
						"pokeapi",
						"co"
					],
					"path": [
						"api",
						"v2",
						"ability"
					],
					"query": [
						{
							"key": "pokemon",
							"value": "charizard"
						}
					]
				}
			},
			"response": []
		},
		{
			"name": "Parte_2_Punto_5",
			"request": {
				"method": "GET",
				"header": [],
				"url": {
					"raw": "https://pokeapi.co/api/v2/pokemon/bulbasaur",
					"protocol": "https",
					"host": [
						"pokeapi",
						"co"
					],
					"path": [
						"api",
						"v2",
						"pokemon",
						"bulbasaur"
					]
				}
			},
			"response": []
		}
	]
}